env_wrappers/__init__.py
env_wrappers/flat_env.py
env_wrappers/monitor.py
env_wrappers/metaworld/__init__.py
env_wrappers/metaworld/mw_env.py
env_wrappers/metaworld/render_env.py
env_wrappers/samplers/__init__.py
env_wrappers/samplers/dummy_runner.py
env_wrappers/samplers/path_gen.py
env_wrappers/samplers/pickle_wrapper.py
env_wrappers/samplers/subproc_runner.py
env_wrappers/vec_env/__init__.py
env_wrappers/vec_env/dummy_vec_env.py
env_wrappers/vec_env/subproc_vec_env.py
env_wrappers/vec_env/tile_images.py
env_wrappers/vec_env/util.py
env_wrappers/vec_env/vec_env.py
env_wrappers-0.1.22.dist-info/LICENSE
env_wrappers-0.1.22.dist-info/METADATA
env_wrappers-0.1.22.dist-info/WHEEL
env_wrappers-0.1.22.dist-info/top_level.txt
env_wrappers-0.1.22.dist-info/RECORD
