Metadata-Version: 2.1
Name: env-wrappers
Version: 0.1.22
Summary: A clean collection of gym environment wrappers
Home-page: UNKNOWN
Author: Ge Yang<ge.ike.yang@gmail.com>
Author-email: UNKNOWN
License: MIT
Platform: UNKNOWN
Requires-Dist: ml-logger
